[
    {
        "pk": 1, 
        "model": "ads.customer", 
        "fields": {
            "name": "Bidule", 
            "modification_date": "2008-10-17 10:27:38", 
            "creation_date": "2008-10-17 10:27:38"
        }
    }, 
    {
        "pk": 2, 
        "model": "ads.customer", 
        "fields": {
            "name": "Chouette", 
            "modification_date": "2008-10-17 10:27:50", 
            "creation_date": "2008-10-17 10:27:50"
        }
    }, 
    {
        "pk": 1, 
        "model": "ads.adcampaign", 
        "fields": {
            "customer": 1, 
            "name": "Bidule Campagne", 
            "modification_date": "2008-10-17 10:28:07", 
            "creation_date": "2008-10-17 10:28:07"
        }
    }, 
    {
        "pk": 2, 
        "model": "ads.adcampaign", 
        "fields": {
            "customer": 2, 
            "name": "Chouette Campagne", 
            "modification_date": "2008-10-17 10:28:15", 
            "creation_date": "2008-10-17 10:28:15"
        }
    },
    {
        "pk": 1, 
        "model": "ads.addefaultbanner", 
        "fields": {
            "description": "", 
            "modification_date": "2008-10-17 13:17:49", 
            "banner": "upload/ads/default/otoprom_728x90.gif", 
            "creation_date": "2008-10-17 13:17:49", 
            "banner_type": "image", 
            "link": "http://www.critica.fr/", 
            "submitter": 1, 
            "banner_extension": "gif", 
            "ads": [
                1, 
                9, 
                14, 
                19, 
                24, 
                28, 
                33, 
                37, 
                42, 
                46, 
                51, 
                56, 
                62, 
                73
            ]
        }
    }, 
    {
        "pk": 2, 
        "model": "ads.addefaultbanner", 
        "fields": {
            "description": "", 
            "modification_date": "2008-10-17 13:23:43", 
            "banner": "upload/ads/default/otoprom_468x60.gif", 
            "creation_date": "2008-10-17 13:23:43", 
            "banner_type": "image", 
            "link": "http://www.critica.fr/", 
            "submitter": 1, 
            "banner_extension": "gif", 
            "ads": [
                3, 
                4, 
                5, 
                10, 
                11, 
                15, 
                16, 
                20, 
                21, 
                25, 
                26, 
                29, 
                30, 
                34, 
                35, 
                38, 
                39, 
                43, 
                44, 
                47, 
                48, 
                52, 
                53, 
                57, 
                64, 
                67, 
                70, 
                74
            ]
        }
    }, 
    {
        "pk": 3, 
        "model": "ads.addefaultbanner", 
        "fields": {
            "description": "", 
            "modification_date": "2008-10-17 13:26:08", 
            "banner": "upload/ads/default/otoprom_250x250.gif", 
            "creation_date": "2008-10-17 13:26:08", 
            "banner_type": "image", 
            "link": "http://www.critica.fr/", 
            "submitter": 1, 
            "banner_extension": "gif", 
            "ads": [
                12, 
                17, 
                22, 
                31, 
                40, 
                49, 
                54, 
                55, 
                58
            ]
        }
    }, 
    {
        "pk": 4, 
        "model": "ads.addefaultbanner", 
        "fields": {
            "description": "", 
            "modification_date": "2008-10-17 13:27:56", 
            "banner": "upload/ads/default/otoprom_300x250.gif", 
            "creation_date": "2008-10-17 13:27:56", 
            "banner_type": "image", 
            "link": "http://www.critica.fr/", 
            "submitter": 1, 
            "banner_extension": "gif", 
            "ads": [
                6, 
                7, 
                59, 
                60, 
                65, 
                66, 
                68, 
                69, 
                71, 
                72, 
                75, 
                76
            ]
        }
    }, 
    {
        "pk": 5, 
        "model": "ads.addefaultbanner", 
        "fields": {
            "description": "", 
            "modification_date": "2008-10-17 13:29:45", 
            "banner": "upload/ads/default/critica-Sky120-otoprom.gif", 
            "creation_date": "2008-10-17 13:29:45", 
            "banner_type": "image", 
            "link": "http://www.critica.fr/", 
            "submitter": 1, 
            "banner_extension": "gif", 
            "ads": [
                8, 
                13, 
                18, 
                23, 
                27, 
                32, 
                36, 
                41, 
                45, 
                50, 
                61, 
                63, 
                77
            ]
        }
    }, 
    {
        "pk": 1, 
        "model": "ads.adbanner", 
        "fields": {
            "description": "Super Banni\u00e8re 728x90.", 
            "campaign": 1, 
            "banner": "upload/ads/2008/10/17/728x90.jpg", 
            "ads": [
                1, 
                9, 
                14, 
                19, 
                24, 
                28, 
                33, 
                37, 
                42, 
                46, 
                51, 
                56, 
                62, 
                73
            ], 
            "creation_date": "2008-10-17 10:30:58", 
            "banner_type": "image", 
            "ending_date": "2008-11-12", 
            "link": "http://www.google.com/", 
            "type": 1, 
            "submitter": 1, 
            "starting_date": "2008-09-10", 
            "banner_extension": "jpg", 
            "modification_date": "2008-10-17 10:30:58"
        }
    }, 
    {
        "pk": 2, 
        "model": "ads.adbanner", 
        "fields": {
            "description": "Super Banni\u00e8re 468x60.", 
            "campaign": 1, 
            "banner": "upload/ads/2008/10/17/468x60.jpg", 
            "ads": [
                3, 
                4, 
                5, 
                10, 
                11, 
                15, 
                16, 
                20, 
                21, 
                25, 
                26, 
                29, 
                30, 
                34, 
                35, 
                38, 
                39, 
                43, 
                44, 
                47, 
                48, 
                52, 
                53, 
                57, 
                64, 
                67, 
                70, 
                74
            ], 
            "creation_date": "2008-10-17 10:34:14", 
            "banner_type": "image", 
            "ending_date": "2008-11-28", 
            "link": "", 
            "type": 1, 
            "submitter": 1, 
            "starting_date": "2008-09-30", 
            "banner_extension": "jpg", 
            "modification_date": "2008-10-17 10:34:14"
        }
    }, 
    {
        "pk": 1, 
        "model": "ads.adbanner", 
        "fields": {
            "description": "Super Banni\u00e8re 728x90.", 
            "campaign": 1, 
            "banner": "upload/ads/2008/10/17/728x90.jpg", 
            "ads": [
                1, 
                9, 
                14, 
                19, 
                24, 
                28, 
                33, 
                37, 
                42, 
                46, 
                51, 
                56, 
                62, 
                73
            ], 
            "creation_date": "2008-10-17 10:30:58", 
            "banner_type": "image", 
            "ending_date": "2008-11-12", 
            "link": "http://www.google.com/", 
            "type": 1, 
            "submitter": 1, 
            "starting_date": "2008-09-10", 
            "banner_extension": "jpg", 
            "modification_date": "2008-10-17 10:30:58"
        }
    }, 
    {
        "pk": 2, 
        "model": "ads.adbanner", 
        "fields": {
            "description": "Super Banni\u00e8re 468x60.", 
            "campaign": 1, 
            "banner": "upload/ads/2008/10/17/468x60.jpg", 
            "ads": [
                3, 
                4, 
                5, 
                10, 
                11, 
                15, 
                16, 
                20, 
                21, 
                25, 
                26, 
                29, 
                30, 
                34, 
                35, 
                38, 
                39, 
                43, 
                44, 
                47, 
                48, 
                52, 
                53, 
                57, 
                64, 
                67, 
                70, 
                74
            ], 
            "creation_date": "2008-10-17 10:34:14", 
            "banner_type": "image", 
            "ending_date": "2008-11-28", 
            "link": "", 
            "type": 1, 
            "submitter": 1, 
            "starting_date": "2008-09-30", 
            "banner_extension": "jpg", 
            "modification_date": "2008-10-17 10:34:14"
        }
    }, 
    {
        "pk": 3, 
        "model": "ads.adbanner", 
        "fields": {
            "description": "", 
            "campaign": 1, 
            "banner": "upload/ads/2008/10/17/300x90.jpg", 
            "ads": [
                6, 
                7, 
                59, 
                60, 
                65, 
                66, 
                68, 
                69, 
                71, 
                72, 
                75, 
                76
            ], 
            "creation_date": "2008-10-17 10:58:19", 
            "banner_type": "image", 
            "ending_date": "2008-12-19", 
            "link": "", 
            "type": 1, 
            "submitter": 1, 
            "starting_date": "2008-10-10", 
            "banner_extension": "jpg", 
            "modification_date": "2008-10-17 10:58:19"
        }
    }, 
    {
        "pk": 4, 
        "model": "ads.adbanner", 
        "fields": {
            "description": "", 
            "campaign": 2, 
            "banner": "upload/ads/2008/10/17/250x250.jpg", 
            "ads": [
                12, 
                17, 
                22, 
                31, 
                40, 
                49, 
                54, 
                58
            ], 
            "creation_date": "2008-10-17 11:00:27", 
            "banner_type": "image", 
            "ending_date": "2009-01-15", 
            "link": "http://www.google.com/", 
            "type": 1, 
            "submitter": 1, 
            "starting_date": "2008-09-10", 
            "banner_extension": "jpg", 
            "modification_date": "2008-10-17 11:00:27"
        }
    }, 
    {
        "pk": 5, 
        "model": "ads.adbanner", 
        "fields": {
            "description": "", 
            "campaign": 2, 
            "banner": "upload/ads/2008/10/17/120x600.jpg", 
            "ads": [
                8, 
                13, 
                18, 
                23, 
                27, 
                32, 
                36, 
                41, 
                45, 
                50, 
                61, 
                63, 
                77
            ], 
            "creation_date": "2008-10-17 11:04:43", 
            "banner_type": "image", 
            "ending_date": "2008-12-19", 
            "link": "", 
            "type": 1, 
            "submitter": 1, 
            "starting_date": "2008-09-10", 
            "banner_extension": "jpg", 
            "modification_date": "2008-10-17 11:04:43"
        }
    }
]
